setup.py
test/test_administrator.py
test/test_authentication.py
test/test_campaign.py
test/test_client.py
test/test_createsend.py
test/test_list.py
test/test_people.py
test/test_segment.py
test/test_subscriber.py
test/test_template.py
test/test_transactional.py
test/test_verifiedhttpsconnection.py
vtscreatesend/__init__.py
vtscreatesend/administrator.py
vtscreatesend/cacert.pem
vtscreatesend/campaign.py
vtscreatesend/client.py
vtscreatesend/createsend.py
vtscreatesend/list.py
vtscreatesend/person.py
vtscreatesend/segment.py
vtscreatesend/subscriber.py
vtscreatesend/template.py
vtscreatesend/transactional.py
vtscreatesend/utils.py
vtscreatesend.egg-info/PKG-INFO
vtscreatesend.egg-info/SOURCES.txt
vtscreatesend.egg-info/dependency_links.txt
vtscreatesend.egg-info/requires.txt
vtscreatesend.egg-info/top_level.txt