Metadata-Version: 1.0
Name: vtscreatesend
Version: 0.0.1
Summary: fixed version of a library which implements the complete functionality of the Campaign Monitor API.
Home-page: http://campaignmonitor.github.io/createsend-python/
Author: James Dennes
Author-email: jdennes@gmail.com
License: MIT
Keywords: createsend campaign monitor email
Platform: UNKNOWN
